uncoverml/__init__.py
uncoverml/cluster.py
uncoverml/config.py
uncoverml/cubist.py
uncoverml/cubist_config.py
uncoverml/diagnostics.py
uncoverml/features.py
uncoverml/filtering.py
uncoverml/geoio.py
uncoverml/image.py
uncoverml/interpolate.py
uncoverml/krige.py
uncoverml/learn.py
uncoverml/likelihoods.py
uncoverml/metadata_profiler.py
uncoverml/mllog.py
uncoverml/models.py
uncoverml/mpiops.py
uncoverml/patch.py
uncoverml/predict.py
uncoverml/resampling.py
uncoverml/targets.py
uncoverml/validate.py
uncoverml/optimise/__init__.py
uncoverml/optimise/models.py
uncoverml/optimise/scorers.py
uncoverml/scripts/__init__.py
uncoverml/scripts/cluster_cli.py
uncoverml/scripts/covdiag_cli.py
uncoverml/scripts/gammasensor_cli.py
uncoverml/scripts/gridsearch_cli.py
uncoverml/scripts/learn_cli.py
uncoverml/scripts/modelfix_cli.py
uncoverml/scripts/predict_cli.py
uncoverml/scripts/resample_cli.py
uncoverml/scripts/shiftmap_cli.py
uncoverml/scripts/subsample_cli.py
uncoverml/scripts/targetsearch_cli.py
uncoverml/scripts/tiff2kmz_cli.py
uncoverml/transforms/__init__.py
uncoverml/transforms/impute.py
uncoverml/transforms/linear.py
uncoverml/transforms/onehot.py
uncoverml/transforms/target.py
uncoverml/transforms/transformset.py
uncover_ml-0.4.0.dist-info/AUTHORS.rst
uncover_ml-0.4.0.dist-info/LICENSE
uncover_ml-0.4.0.dist-info/METADATA
uncover_ml-0.4.0.dist-info/WHEEL
uncover_ml-0.4.0.dist-info/entry_points.txt
uncover_ml-0.4.0.dist-info/top_level.txt
uncover_ml-0.4.0.dist-info/RECORD
